attribox/__init__.py
attribox/_abstract_descriptor.py
attribox/_attri_box.py
attribox/_attri_class.py
attribox/_attrify.py
attribox/_delayed_descriptor.py
attribox/_this_scope.py
attribox/_typed_descriptor.py
example/__init__.py
example/_point.py
example/_rectangle.py
example/main.py
attribox-0.1.33.dist-info/LICENSE
attribox-0.1.33.dist-info/METADATA
attribox-0.1.33.dist-info/WHEEL
attribox-0.1.33.dist-info/top_level.txt
attribox-0.1.33.dist-info/RECORD
