Metadata-Version: 2.1
Name: attribox
Version: 0.1.33
Summary: Allows for deferred instantiation of class attributes.
Home-page: https://github.com/AsgerJon/attribox
Author: Asger Jon Vistisen
Author-email: Asger Jon Vistisen <asgerjon2@gmail.com>
Project-URL: Homepage, https://github.com/AsgerJon/attribox
Project-URL: Bug Tracker, https://github.com/AsgerJon/attribox
Classifier: Programming Language :: Python :: 3
Classifier: License :: OSI Approved :: GNU Affero General Public License v3 or later (AGPLv3+)
Classifier: Operating System :: OS Independent
Requires-Python: >=3.9
License-File: LICENSE
